setup.py
PraktickaKnihovna/Praktika.py
PraktickaKnihovna/__init__.py
praktickaKnihovna.egg-info/PKG-INFO
praktickaKnihovna.egg-info/SOURCES.txt
praktickaKnihovna.egg-info/dependency_links.txt
praktickaKnihovna.egg-info/top_level.txt