Metadata-Version: 2.1
Name: praktickaKnihovna
Version: 0.0.5
Summary: Moje mala knihovna na praktika
Home-page: 
Author: Brystof_Klazek
Author-email: blazekr2@cvut.cz
Classifier: Programming Language :: Python :: 3
Classifier: License :: OSI Approved :: MIT License
Classifier: Operating System :: OS Independent
